{
"Shade:Strike_Shade": {
    "NAME": "Удар",
    "DESCRIPTION": "Наносит !D! урона.",
    "UPGRADE_DESCRIPTION": "Наносит !D! урона."
  },
"Shade:Defend_Shade": {
    "NAME": "Оборона",
    "DESCRIPTION": "Даёт !B! Защиты.",
    "UPGRADE_DESCRIPTION": "Даёт !B! Защиты."
  },
"Shade:AnimateDead": {
    "NAME": "Поднять мёртвых",
    "DESCRIPTION": "Призывается !M! shade:Зомби и 2 shade:Скелета.",
    "UPGRADE_DESCRIPTION": "Призывается !M! shade:Зомби и 2 shade:Скелета."
  },
"Shade:ClawBack": {
    "NAME": "Полоснуть когтем",
    "DESCRIPTION": "Наносит !D! урона. NL Случайная shade:Погребённая карта возвращается в стопку добора.",
    "UPGRADE_DESCRIPTION": "Наносит !D! урона. NL Случайная shade:Погребённая карта возвращается в стопку добора"
  },
  "Shade:AblativeArmor": {
    "NAME": "Аблативная броня",
    "DESCRIPTION": "Жертвуется shade:Зомби. Накладывает !M! Слабости на всех врагов и даёт 1 Ловкости.",
    "UPGRADE_DESCRIPTION": "Жертвуется shade:Зомби. Накладывает !M! Слабости на всех врагов и даёт 1 Ловкости.",
    "EXTENDED_DESCRIPTION": ["Мне нужны shade:Зомби."]
  },
  "Shade:Boneskin": {
    "NAME": "Костяная оболочка",
    "DESCRIPTION": "Жертвуется shade:Зомби. Даёт по 2 панциря за кадого принесённого в жертву shade:Зомби.",
    "UPGRADE_DESCRIPTION": "Жертвуется shade:Зомби. Даёт по 3 панциря за кадого принесённого в жертву shade:Зомби.",
    "EXTENDED_DESCRIPTION": ["Мне нужны shade:Зомби."]
  },
  "Shade:FreshBones": {
    "NAME": "Свежие кости",
    "DESCRIPTION": "Призывается shade:Скелет. NL shade:Скелеты наносят на 3 больше урона, на !M! ход.",
    "UPGRADE_DESCRIPTION": "Призывается shade:Скелет. NL shade:Скелеты наносят на 3 больше урона, на !M! хода."
  },
  "Shade:TouchOfTheGrave": {
    "NAME": "Мёртвое возмездие",
    "DESCRIPTION": "В начале вашего хода, разыгрывается случайная shade:Погребённая Атака, а затем shade:Изгоняется.",
    "UPGRADE_DESCRIPTION": "В начале вашего хода, разыгрывается случайная shade:Погребённая Атака и возвращается в стопку сброса."
  },
  "Shade:CallOfTheGrave": {
    "NAME": "Зов могилы",
    "DESCRIPTION": "В начале вашего хода, разыгрывается случайный shade:Погребённый Навык и shade:Изгоняется.",
    "UPGRADE_DESCRIPTION": "Начальная. NL разыгрывается случайный shade:Погребённый Навык и shade:Изгоняется."
  },
  "Shade:Bonestorm": {
    "NAME": "Костяной шторм",
    "DESCRIPTION": "Наносит !D! урона всем врагам. NL Призывается !M! shade:Скелет.",
    "UPGRADE_DESCRIPTION": "Наносит !D! урона всем врагам. NL Призывается !M! shade:Скелета."
  },
  "Shade:WallOfFlesh": {
    "NAME": "Стена из плоти",
    "DESCRIPTION": "Призывается !M! shade:Зомби. Даёт !B! Защиты.",
    "UPGRADE_DESCRIPTION": "Призывается !M! shade:Зомби. Даёт !B! Защиты."
  },
  "Shade:FingerOfDeath": {
    "NAME": "Перст смерти",
    "DESCRIPTION": "Наносит !D! урона. NL Если убивает врага, призывается 2 shade:Зомби.",
    "UPGRADE_DESCRIPTION": "Наносит !D! урона. NL Если убивает врага, призывается 2 shade:Зомби."
  },
    "Shade:RavenousHorde": {
    "NAME": "Ненасытная орда",
    "DESCRIPTION": "Вы теряете !M! ОЗ. NL Призывается 2 X shade:Зомби.",
    "UPGRADE_DESCRIPTION": "Вы теряете !M! ОЗ. NL Призывается  2 X + 1 shade:Зомби."
  },
    "Shade:LichForm": {
    "NAME": "Облик лича",
    "DESCRIPTION": "В начале каждого вашего хода, призывается !M! shade:Скелета.",
    "UPGRADE_DESCRIPTION": "В начале вашего хода, призывается !M! shade:Скелетов."
  },
  "Shade:CallWraith": {
    "NAME": "Призвать призрака",
    "DESCRIPTION": "Вы теряете !M! ОЗ. NL Призывается shade:Призрак. NL Сжигается",
    "UPGRADE_DESCRIPTION": "Вы теряете !M! ОЗ. NL Призывается shade:Призрак. NL Сжигается"
  },
  "Shade:Bite_Shade": {
    "NAME": "Укус",
    "DESCRIPTION": "Наносит !D! урона. NL Восполняет !M! ОЗ.",
    "UPGRADE_DESCRIPTION": "Наносит !D! урона. NL Восполняет !M! ОЗ."
  },
  "Shade:RitualOffering": {
    "NAME": "Ритуальное подношение",
    "DESCRIPTION": "Сжигает до !M! выбранных карт из стопки добора. NL Сжигается.",
    "UPGRADE_DESCRIPTION": "Сжигает до !M! выбранных карт из стопки добора. NL Сжигается. NL Вы берёте карту. NL Сжигается."
  },
  "Shade:Frenzy": {
    "NAME": "Бешенство",
    "DESCRIPTION": "Даёт !M! Силы и Ловкости в этот ход. NL Сжигается.",
    "UPGRADE_DESCRIPTION": "Даёт !M! Силы и Ловкости в этот ход. NL Сжигается."
  },
  "Shade:ExtraLimbs": {
    "NAME": "Дополнительные конечности",
    "DESCRIPTION": "Наносит !D! урона !M! раза. NL Когда Сжигается, увеличивает количество ударов на 1 в этом бою. NL Сжигается.",
    "UPGRADE_DESCRIPTION": "Наносит !D! урона !M! раз. NL Когда Сжигается, увеличивает количество ударов на 1 в этом бою. NL Сжигается."
  },
  "Shade:SelfBurial": {
    "NAME": "Самозахоронение",
    "DESCRIPTION": "Возвращает все shade:Погребённые карты в колоду. Сжигает все карты в руке и ещё 10 карт в колоде. NL Вы берёте !M! карты. NL Сжигается.",
    "UPGRADE_DESCRIPTION": "Возвращает все shade:Погребённые карты в колоду. Сжигает все карты в руке и ещё 10 карт в колоде. NL Вы берёте !M! карт. NL Сжигается."
  },
  "Shade:GreyBargain": {
    "NAME": "Серая сделка",
    "DESCRIPTION": "Возвращает shade:Погребённую карту в стопку добора. Сжигает карту в руке.",
    "UPGRADE_DESCRIPTION": "Возвращает shade:Погребённую карту в стопку добора. Сжигает карту в руке. NL Вы берёте карту.",
    "EXTENDED_DESCRIPTION": ["Мне нужно Сжечь ещё."]
  },
  "Shade:FleshLikeOak": {
    "NAME": "Дубовая плоть",
    "DESCRIPTION": "Даёт !B! Защиты. NL Даёт !M! Силы. NL Сжигается.",
    "UPGRADE_DESCRIPTION": "Даёт !B! Защиты. NL Даёт !M! Силы. NL Сжигается."
  },
  "Shade:CloudOfShrapnel": {
    "NAME": "Облако шрапнели",
    "DESCRIPTION": "Жертвуется shade:Скелет. Наносит !D! урона всем врагам и даёт !M! Ловкости. NL Сжигается.",
    "UPGRADE_DESCRIPTION": "Жертвуется shade:Скелет. Наносит !D! урона всем врагам и даёт !M! Ловкости. NL Сжигается.",
    "EXTENDED_DESCRIPTION": ["Мне нужен shade:Skeleton."]
  },
  "Shade:SanguineRitual": {
    "NAME": "Ритуал Сангвина",
    "DESCRIPTION": "Вы теряете 2 ОЗ. NL Даёт [E] [E]. NL Сжигается.",
    "UPGRADE_DESCRIPTION": "Вы теряете 2 ОЗ. NL Даёт [E] [E] [E]. NL Сжигается."
  },
  "Shade:AncientSpear": {
    "NAME": "Древнее копьё",
    "DESCRIPTION": "Наносит !D! урона. NL Сжигается.",
    "UPGRADE_DESCRIPTION": "Наносит !D! урона. NL Сжигается."
  },
  "Shade:FuneraryArmor": {
    "NAME": "Погребальная броня",
    "DESCRIPTION": "Даёт !B! Защиты. NL Сжигается.",
    "UPGRADE_DESCRIPTION": "Даёт !B! Защиты. NL Сжигается."
  },
  "Shade:FuneraryJewels": {
    "NAME": "Погребальные драгоценности",
    "DESCRIPTION": "Даёт !B! Защиты. Вы берёте !M! карту. Даёт [E]. NL Сжигается.",
    "UPGRADE_DESCRIPTION": "Даёт !B! Защиты. Вы берёте !M! карту. Даёт [E]. NL Сжигается."
  },
  "Shade:DangerousRitual": {
    "NAME": "Опасный ритуал",
    "DESCRIPTION": "Наносит !D! урона всем врагам. NL Стоит на 1 меньше за каждые !M! Сожжённые карты в этом бою.",
    "UPGRADE_DESCRIPTION": "Наносит !D! урона всем врагам. NL Стоит на 1 меньше за каждые !M! Сожжённые карты в этом бою."
  },
  "Shade:OminousRitual": {
    "NAME": "Зловещий ритуал",
    "DESCRIPTION": "Даёт Защиту и наносит урон всем врагам равный количеству Сожжённых карт в этом бою.",
    "UPGRADE_DESCRIPTION": "Добавляет 3 *Головокружения в руку. NL Даёт Защиту и наносит урон всем врагам равный количеству Сожжённых карт в этом бою.",
  	"EXTENDED_DESCRIPTION": [" NL ( !M! карт )"]
  },
  "Shade:CommandSoldier": {
    "NAME": "Приказ солдатам",
    "DESCRIPTION": "Призывается shade:Скелет. Задействует !M! атаки shade:Скелета.",
    "UPGRADE_DESCRIPTION": "Призывается shade:Скелет. Задействует !M! атаки shade:Скелетов."
  },
  "Shade:SkeletonArmy": {
    "NAME": "Армия скелетов",
    "DESCRIPTION": "Призывается !M! shade:Скелетов.",
    "UPGRADE_DESCRIPTION": "Призывается !M! shade:Скелетов."
  },
  "Shade:LyeBath": {
    "NAME": "Щелочная ванна",
    "DESCRIPTION": "Преобразовывает всех shade:Зомби в shade:Скелетов. NL Вы берёте карту.",
    "UPGRADE_DESCRIPTION": "Преобразовывает всех shade:Зомби в shade:Скелетов. NL Вы берёте 2 карты."
  },
  "Shade:GoDigging": {
    "NAME": "Пойти на раскопки",
    "DESCRIPTION": "Жертвуется !M! shade:Скелета. В начале следующего хода, призывается 2 shade:Зомби за каждого принесённого в жерту скелета.",
    "UPGRADE_DESCRIPTION": "Жертвуется !M! shade:Скелета. В начале следующего хода, призывается 2 shade:Зомби за каждого принесённого в жертву скелета."
  },
  "Shade:AuraOfUnlife": {
    "NAME": "Аура нежити",
    "DESCRIPTION": "Увеличивает константу разложения на 2, замедляя разложение shade:Зомби и shade:Скелетов.",
    "UPGRADE_DESCRIPTION": "Увеличивает константу разложения на 2, замедляя разложение shade:Зомби и shade:Скелетов.",
    "EXTENDED_DESCRIPTION": [" NL ( 1/ !M! в ход )"]
  },
  "Shade:GraveStillness": {
    "NAME": "Гробовая тишина",
    "DESCRIPTION": "Даёт !B! Защиты. NL shade:Зомби и shade:Скелеты разлагаются на !M! меньше в этот ход.",
    "UPGRADE_DESCRIPTION": "Даёт !B! Защиты. NL shade:Зомби и shade:Скелеты разлагаются на !M! меньше в этот ход."
  },
  "Shade:PotionOfRestlessness": {
    "NAME": "Зелье безумия",
    "DESCRIPTION": "Даёт 3 Силы. NL Уменьшает константу разложения на 1, ускоряя разложение shade:Зомби и shade:Скелетов.",
    "UPGRADE_DESCRIPTION": "Даёт 4 Силы. NL Уменьшает константу разложения на 1, ускоряя разложение shade:Зомби и shade:Скелетов.",
    "EXTENDED_DESCRIPTION": [" NL ( 1/ !M! в ход )"]
  },
  "Shade:GreaterAnimation": {
    "NAME": "Величайшее возрождение",
    "DESCRIPTION": "Призывается 1 shade:Зомби, !M! shade:Скелета, и 1 shade:Призрак. NL Вы теряете 1 Силы и 1 Ловкости.",
    "UPGRADE_DESCRIPTION": "Призывается 1 shade:Зомби, !M! shade:Скелета, и 1 shade:Призрак."
  },
  "Shade:OfferingToTheBeyond": {
    "NAME": "Подношение потустороннему",
    "DESCRIPTION": "Когда Сжигается !M! карты за один ход, призывается shade:Призрак.",
    "UPGRADE_DESCRIPTION": "Когда Сжигается !M! карты за один ход, призывается shade:Призрак."
  },
  "Shade:SoulPierce": {
    "NAME": "Копьё души",
    "DESCRIPTION": "shade:Призраки наносят на !M! больше урона.",
    "UPGRADE_DESCRIPTION": "shade:Призраки наносят на !M! больше урона."
  },
  "Shade:OpenGraves": {
    "NAME": "Разрытые могилы",
    "DESCRIPTION": "В начале вашего хода, поочерёдно, призывается shade:Зомби или shade:Скелет.",
    "UPGRADE_DESCRIPTION": "Призывается shade:Скелета. NL В начале вашего хода, поочерёдно, призывается shade:Зомби или shade:Скелет."
  },
  "Shade:SensePrey": {
    "NAME": "Предчувствие обречённого",
    "DESCRIPTION": "Призывается shade:Зомби и shade:Скелет за каждого врага в бою. NL Сжигается.",
    "UPGRADE_DESCRIPTION": "Начальная. NL Призывается shade:Зомби и shade:Скелет за каждого врага в бою. NL Сжигается."
  },
  "Shade:Trample": {
    "NAME": "Топтать",
    "DESCRIPTION": "Наносит урон, равный !M! и помноженный на количество shade:Зомби.",
    "UPGRADE_DESCRIPTION": "Наносит урон, равный !M! и помноженный на количество shade:Зомби.",
    "EXTENDED_DESCRIPTION": [" NL ( !D! урона )"]
  },
  "Shade:PressTheAttack": {
    "NAME": "Боевой нажим",
    "DESCRIPTION": "Наносит !D! урона. NL shade:Скелеты наносят на 3 больше урона, на 1 ход.",
    "UPGRADE_DESCRIPTION": "Наносит !D! урона. NL shade:Скелеты наносят на 3 больше урона, на 1 ход."
  },
  "Shade:Patience": {
    "NAME": "Терпение",
    "DESCRIPTION": "Вы Оставляете все карты в руке в конце вашего хода.",
    "UPGRADE_DESCRIPTION": "Вы Оставляете все карты в руке в конце вашего хода и оставшуюся энергию."
  },
  "Shade:Awaken": {
    "NAME": "Пробудить",
    "DESCRIPTION": "Перед следующим ходом вы выбираете shade:Погребённую карту и возвращаете её в руку. NL Сжигается.",
    "UPGRADE_DESCRIPTION": "Перед следующим ходом вы выбираете shade:Погребённую карту и возвращаете её в руку. NL Сжигается."
  },
  "Shade:Haruspicy": {
    "NAME": "Гаруспик",
    "DESCRIPTION": "Вы Предсказываете 5 карт и берёте 2 карты. NL Вы жертвуете shade:Зомби или теряете 4 ОЗ.",
    "UPGRADE_DESCRIPTION": "Вы Предсказываете 6 карт и берёте 3 карты. NL Вы жертвуете shade:Зомби или теряете 4 ОЗ."
  },
  "Shade:Brains": {
    "NAME": "Мозги",
    "DESCRIPTION": "Призывается shade:Зомби. NL Вы берёте 2 карты.",
    "UPGRADE_DESCRIPTION": "Призывается 2 shade:Зомби. NL Вы берёте 2 карты."
  },
  "Shade:ScuttlingHand": {
    "NAME": "Бегущая рука",
    "DESCRIPTION": "Наносит !D! урона. NL Возвращается из стопки сброса в руку, когда вы разыгрываете карту, которая Сжигается.",
    "UPGRADE_DESCRIPTION": "Наносит !D! урона. NL Возвращается из стопки сброса в руку, когда вы разыгрываете карту, которая Сжигается."
  },
  "Shade:Premonition": {
    "NAME": "Предчувствие",
    "DESCRIPTION": "Даёт !B! Защиты. NL Каждый раз, когда призывается shade:Призрак, возвращается в руку.",
    "UPGRADE_DESCRIPTION": "Даёт !B! Защиты. NL Каждый раз, когда призывается shade:Призрак, возвращается в руку."
  },
  "Shade:SkeletonHug": {
    "NAME": "Объятия скелета",
    "DESCRIPTION": "Призывается shade:Скелет. NL Наносит !D! урона. NL Накладывает !M! Слабости.",
    "UPGRADE_DESCRIPTION": "Призывается shade:Скелет. NL Наносит !D! урона. NL Накладывает !M! Слабости."
  },
  "Shade:BoneShards": {
    "NAME": "Осколки кости",
    "DESCRIPTION": "Жертвуется !M! shade:Скелета. Наносит !D! урона за каждого принесённого в жертву shade:Скелета.",
    "UPGRADE_DESCRIPTION": "Жертвуется !M! shade:Скелета. Наносит !D! урона за каждого принесённого в жертву shade:Скелета."
  },
  "Shade:CoffinDance": {
    "NAME": "Танец с гробом",
    "DESCRIPTION": "Наносит !D! урона. NL Если общее количество shade:Зомби или shade:Скелетов кратно 4, призывается !M! shade:Зомби.",
    "UPGRADE_DESCRIPTION": "Наносит !D! урона. NL Если общее количество shade:Зомби или shade:Скелетов кратно 4, призывается !M! shade:Зомби."
  },
  "Shade:UnbarTheGrave": {
    "NAME": "Разрыть капище",
    "DESCRIPTION": "Призывается !M! shade:Зомби и !M! shade:Скелета. NL Верните !M! случайные shade:Погребённые карты в стопку добора. NL Сжигается.",
    "UPGRADE_DESCRIPTION": "Призывается !M! shade:Зомби и !M! shade:Скелета. NL Верните !M! случайные shade:Погребённые карты в стопку добора. NL Сжигается."
  },
  "Shade:Carnophage": {
    "NAME": "Карнофаг",
    "DESCRIPTION": "Каждый раз, когда вы берёте карту Проклятия или Статуса, призывается shade:Зомби.",
    "UPGRADE_DESCRIPTION": "Каждый раз, когда вы берёте карту Проклятья или Статуса, призывается shade:Зомби."
  },
  "Shade:Excise": {
    "NAME": "Вырезать",
    "DESCRIPTION": "Даёт !B! Защиты. NL Сжигает карту. Если Сжигается Статус или Проклятье, Вы получаете [E] и берёте карту.",
    "UPGRADE_DESCRIPTION": "Даёт !B! Защиты. NL Сжигает карту. Если Сжигается Статус или Проклятье, Вы получаете [E] и берёте карту."
  },
  "Shade:StitchTogether": {
    "NAME": "Сшить воедино",
    "DESCRIPTION": "В следующий раз, когда вы возьмёте карту Cтатуса или Проклятия, Сожгите их, возьмите карту, и восполните !M! ОЗ.",
    "UPGRADE_DESCRIPTION": "В следующий раз, когда вы возьмёте карту Cтатуса или Проклятия, Сожгите их, возьмите карту, и восполните !M! ОЗ."
  },
  "Shade:FleshToFlesh": {
    "NAME": "Плоть от плоти",
    "DESCRIPTION": "Призывается !M! shade:Зомби. NL Добавляет *Рану в стопку сброса.",
    "UPGRADE_DESCRIPTION": "Призывается !M! shade:Зомби. NL Добавляет *Рану в стопку сброса."
  },
  "Shade:LoseControl": {
    "NAME": "Потеря контроля",
    "DESCRIPTION": "Добавляет 2 *Раны в стопку сброса. NL Вы берёте !M! карты.",
    "UPGRADE_DESCRIPTION": "Добавляет 2 *Раны в стопку сброса. NL Вы берёте !M! карты."
  },
  "Shade:FleshOffering": {
    "NAME": "Подношение плоти",
    "DESCRIPTION": "Призывается shade:Призрак. NL Даёт !B! Защиты. NL Добавляет 4 *Раны в стопку сброса.",
    "UPGRADE_DESCRIPTION": "Призывается shade:Призрак. NL Даёт !B! Защиты. NL Добавляет 4 *Раны в стопку сброса."
  },
  "Shade:FeralStrike": {
    "NAME": "Похоронный удар",
    "DESCRIPTION": "Наносит !D! урона всем врагам. NL Добавляет *Рану в руку. NL Сжигается.",
    "UPGRADE_DESCRIPTION": "Наносит !D! урона всем врагам. NL Добавляет *Рану в руку. NL Сжигается."
  },
  "Shade:DarkOfNight": {
    "NAME": "Ночная тьма",
    "DESCRIPTION": "Следующая карта, которая Сжигается в этом ходу, разыгрывается дважды.",
    "UPGRADE_DESCRIPTION": "Следующие 2 карты, которые Сжигаются в этом ходу, разыгрываются дважды."
  },
  "Shade:Tombstone": {
    "NAME": "Надгробие",
    "DESCRIPTION": "Наносит !D! урона. NL Сжигается.",
    "UPGRADE_DESCRIPTION": "Наносит !D! урона. NL Сжигается."
  },
  "Shade:Putrefaction": {
    "NAME": "Гниение",
    "DESCRIPTION": "shade:Зомби накладывают !M! Яда на всех врагов, когда погибают.",
    "UPGRADE_DESCRIPTION": "shade:Зомби накладывают !M! Яда на всех врагов, когда погибают."
  },
  "Shade:PoundOfFlesh": {
    "NAME": "Фунт плоти",
    "DESCRIPTION": "Наносит !D! урона. NL На следующий ход, призывается !M! shade:Зомби.",
    "UPGRADE_DESCRIPTION": "Наносит !D! урона. NL На следующий ход, призывается !M! shade:Зомби."
  },
  "Shade:Doomsay": {
    "NAME": "Фатум",
    "DESCRIPTION": "Наносит !D! урона дважды. NL Предскажите !M! карты.",
    "UPGRADE_DESCRIPTION": "Наносит !D! урона дважды. NL Предскажите !M! карт."
  },
  "Shade:Consume": {
    "NAME": "Поглотить",
    "DESCRIPTION": "Сжигает !M! карты с верха стопки добора. NL Добавляет !M! *Раны в стопку сброса. NL Наносит !D! урона всем врагам.",
    "UPGRADE_DESCRIPTION": "Сжигает !M! карты с верха стопки добора. NL Добавляет !M! *Раны в стопку сброса. NL Наносит !D! урона всем врагам."
  },
  "Shade:Coordination": {
    "NAME": "Координирование",
    "DESCRIPTION": "Атаки shade:Скелетов бьют по всем врагам.",
    "UPGRADE_DESCRIPTION": "Атаки shade:Скелетов бьют по всем врагам. NL Задействует 2 атаки shade:Скелетов."
  },
  "Shade:SoulToxin": {
    "NAME": "Токсин духа",
    "DESCRIPTION": "Накладывает 2 Слабости. NL Цель теряет 3 ОЗ. NL Если призван shade:Призрак, накладывает !M! Яда.",
    "UPGRADE_DESCRIPTION": "Накладывает 3 Слабости. NL Цель теряет 5 ОЗ. NL Если призван shade:Призрак, накладывает !M! Яда."
  },
  "Shade:Asphyxiate": {
    "NAME": "Удушение",
    "DESCRIPTION": "Накладывает !M! Яда. NL Наносит урон, равный количеству Яда на враге. NL Сжигается.",
    "UPGRADE_DESCRIPTION": "Накладывает !M! Яда. NL Наносит урон, равный количеству Яда на враге. NL Сжигается.",
    "EXTENDED_DESCRIPTION": [" NL ( !D! урона )"]
  },
  "Shade:SpontaneousRitual": {
    "NAME": "Спонтанный ритуал",
    "DESCRIPTION": "Сжигает все карты в руке. NL Наносит урон, равный количеству сожённых карт в этом бою.",
    "UPGRADE_DESCRIPTION": "Добавляет 3 *Головокружения в руку. NL Сжигает все карты в руке. NL Наносит урон, равный количеству сожённых карт в этом бою.",
  	"EXTENDED_DESCRIPTION": [" NL ( !M! карт уже )"]
  },
  "Shade:CarefulCut": {
    "NAME": "Осторожный надрез",
    "DESCRIPTION": "Наносит !D! урона. NL Вы берёте 1 карту. NL Сжигает карту.",
    "UPGRADE_DESCRIPTION": "Наносит !D! урона. NL Вы берёте 1 карту. NL Сжигает карту."
  },
  "Shade:MadHubris": {
    "NAME": "Лунное помешательство",
    "DESCRIPTION": "Призывается !M! shade:Скелетов. NL Перед вашим следующим ходом, ваши shade:Скелеты атакуют вас.",
    "UPGRADE_DESCRIPTION": "Оставляется. NL Призывается !M! shade:Скелетов. NL Перед вашим следующим ходом, ваши shade:Скелеты атакуют вас."
  },
  "Shade:OneIsEnough": {
    "NAME": "Одного достаточно",
    "DESCRIPTION": "Вы жертвуете всей вашей нежитью. Даёт по !B! Защиты за каждого. NL Наносит !D! урона X раз.",
    "UPGRADE_DESCRIPTION": "Вы жертвуете всей вашей нежитью. Даёт по !B! Защиты за каждого. NL Наносит !D! урона X раз."
  },
  "Shade:LastGasp": {
    "NAME": "Последний вздох",
    "DESCRIPTION": "Эфирная. NL Выберите shade:Погребённую карту, разыграйте её, и shade:Изгоните.",
    "UPGRADE_DESCRIPTION": "Выберите shade:Погребённую карту, разыграйте её, и shade:Изгоните."
  },
  "Shade:SpectralStrikes": {
    "NAME": "Призрачные удары",
    "DESCRIPTION": "Когда разыгрывается карта содержащая \"Удар,\" в названии, она shade:Изгоняется, вы берёте карту и получаете 1 Силы.",
    "UPGRADE_DESCRIPTION": "Начальная. NL Когда разыгрывается карта содержащая \"Удар,\" в названии, она shade:Изгоняется, вы берёте карту и получаете 1 Силы."
  }
}